{"version":1,"resource":"file:///c%3A/Users/User/Documents/projetos-reais/portifolio/src/app/%28home%29/page.tsx","entries":[{"id":"iQjs.tsx","timestamp":1750185752141},{"id":"7puq.tsx","timestamp":1750185915917},{"id":"xqu1.tsx","source":"Add import from \"./components/header/header\"","timestamp":1750185920918},{"id":"8eIy.tsx","timestamp":1750185925691},{"id":"1gjf.tsx","timestamp":1750185938209},{"id":"S3ML.tsx","timestamp":1750188612485},{"id":"ztFh.tsx","timestamp":1750189858399},{"id":"oU1F.tsx","timestamp":1750209657902},{"id":"EhbQ.tsx","timestamp":1750209686251},{"id":"S7EF.tsx","timestamp":1750209696310},{"id":"ih0O.tsx","timestamp":1750210235812},{"id":"HN1u.tsx","source":"undoRedo.source","timestamp":1750210249492},{"id":"2dwV.tsx","timestamp":1750210250336},{"id":"qvOV.tsx","timestamp":1750277673056},{"id":"3alG.tsx","timestamp":1750280460261},{"id":"zi8C.tsx","timestamp":1750280474459},{"id":"idKK.tsx","timestamp":1750280487736},{"id":"xmyY.tsx","timestamp":1750280499104},{"id":"IUgC.tsx","timestamp":1750283396372},{"id":"bxZM.tsx","source":"Add import from \"./components/projects/page\"","timestamp":1750283399536},{"id":"D0zm.tsx","source":"Workspace Edit","timestamp":1750283976903},{"id":"txkI.tsx","timestamp":1750304801589},{"id":"3zPv.tsx","source":"Add import from \"./components/test\"","timestamp":1750304804791},{"id":"XNVG.tsx","source":"undoRedo.source","timestamp":1750304913693},{"id":"Rp2J.tsx","timestamp":1750702893797},{"id":"vA3c.tsx","timestamp":1750707596769},{"id":"zNW1.tsx","source":"Add import from \"./components/experiencia/experiencia\"","timestamp":1750707600486},{"id":"f6dD.tsx","timestamp":1750707631075},{"id":"5hwT.tsx","timestamp":1750707645909},{"id":"hoYq.tsx","timestamp":1750899779117},{"id":"JKIj.tsx","source":"Add import from \"./components/footer/footer\"","timestamp":1750899785374},{"id":"gyjz.tsx","timestamp":1750903902521},{"id":"33ZQ.tsx","timestamp":1751064445021},{"id":"sW3h.tsx","timestamp":1751064472095},{"id":"glCw.tsx","timestamp":1751064492690},{"id":"HlbB.tsx","timestamp":1751064504532},{"id":"qNbn.tsx","timestamp":1751064541938},{"id":"I4E7.tsx","timestamp":1751064617915},{"id":"8bEc.tsx","timestamp":1751064645570},{"id":"Oydm.tsx","timestamp":1751064657562},{"id":"F5Ft.tsx","timestamp":1751064676412},{"id":"wgSU.tsx","timestamp":1751064695176},{"id":"IrSh.tsx","timestamp":1751064717884},{"id":"yD5H.tsx","source":"undoRedo.source","timestamp":1751064734290},{"id":"woJd.tsx","timestamp":1751064756135},{"id":"MrAy.tsx","source":"undoRedo.source","timestamp":1751064758228},{"id":"d4FY.tsx","timestamp":1751064802981},{"id":"gozs.tsx","timestamp":1751065322780},{"id":"Sbbb.tsx","timestamp":1751065346492},{"id":"sKc7.tsx","timestamp":1751065370806}]}